{
  "bg": "https://images.pexels.com/photos/3767825/pexels-photo-3767825.jpeg?auto=compress&cs=tinysrgb&h=750&w=1260",
  "title": "The boy who lived",
  "description": "Teste os seus conhecimentos sobre CSS e vamos ver quantos layouts você vai deixar de quebrar",
  "questions": [
    {
      "image": "https://images.unsplash.com/photo-1547756536-cde3673fa2e5?ixid=MXwxMjA3fDB8MHxwaG90by1wYWdlfHx8fGVufDB8fHw%3D&ixlib=rb-1.2.1&auto=format&fit=crop&w=1111&q=80",
      "title": "Quem é o responsável por jogar o pudim/bolo na sra. mason?",
      "description": "Essa é pra aquecer",
      "answer": 1,
      "alternatives": [
        "sirius black",
        "o elfo doméstico Dobby",
        "harry potter",
        "duda dursley"
      ]
    },
    {
      "image": "https://images.unsplash.com/photo-1551269901-5c5e14c25df7?ixlib=rb-1.2.1&ixid=MXwxMjA3fDB8MHxwaG90by1wYWdlfHx8fGVufDB8fHw%3D&auto=format&fit=crop&w=1350&q=80",
      "title": "Através de que meio de transporte harry chega na toca?",
      "description": "Faz tempo em haha",
      "answer": 3,
      "alternatives": [
         "pó de flu",
         "vassoura",
         "aparatando",
         "carro"
      ]
    }
  ],
  "external": [
    ""
  ],
  "theme": {
    "colors": {
      "primary": "#e63946",
      "secondary": "#ffe808",
      "mainBg": "#171B35",
      "contrastText": "#FFFFFF",
      "wrong": "#eb5e28",
      "success": "#4CAF50"
    },
    "borderRadius": "4px"
  }
}